{
  "name": "cloud_utils",
  "description": "Grabbag of utility cookbooks",
  "long_description": "# cloud_utils chef cookbook\n\nGrabbag of utility cookbooks\n\n## Overview\n\nGrabbag of utility cookbooks\n\n## Recipes \n\n* `burn_ami_prep`            - Burn Ami Prep\n* `pickle_node`              - Write the node metadata out into a file for later use\n* `virtualbox_metadata`      - Virtualbox Metadata\n\n## Integration\n\nSupports platforms: debian and ubuntu\n\n\n\n## Attributes\n\n\n## License and Author\n\nAuthor::                Philip (flip) Kromer - Infochimps, Inc (<coders@infochimps.com>)\nCopyright::             2011, Philip (flip) Kromer - Infochimps, Inc\n\nLicensed under the Apache License, Version 2.0 (the \"License\");\nyou may not use this file except in compliance with the License.\nYou may obtain a copy of the License at\n\n    http://www.apache.org/licenses/LICENSE-2.0\n\nUnless required by applicable law or agreed to in writing, software\ndistributed under the License is distributed on an \"AS IS\" BASIS,\nWITHOUT WARRANTIES OR CONDITIONS OF ANY KIND, either express or implied.\nSee the License for the specific language governing permissions and\nlimitations under the License.\n\n> readme generated by [cluster_chef](http://github.com/infochimps/cluster_chef)'s cookbook_munger\n",
  "maintainer": "Philip (flip) Kromer - Infochimps, Inc",
  "maintainer_email": "coders@infochimps.com",
  "license": "Apache 2.0",
  "platforms": {
    "debian": ">= 0.0.0",
    "ubuntu": ">= 0.0.0"
  },
  "dependencies": {
  },
  "recommendations": {
  },
  "suggestions": {
  },
  "conflicting": {
  },
  "providing": {
  },
  "replacing": {
  },
  "attributes": {
  },
  "groupings": {
  },
  "recipes": {
    "cloud_utils::burn_ami_prep": "Burn Ami Prep",
    "cloud_utils::virtualbox_metadata": "Virtualbox Metadata",
    "cloud_utils::pickle_node": "Write the node metadata out into a file for later use"
  },
  "version": "3.0.4"
}